{
  "build": {
    "context": "..",
    "dockerfile": "Dockerfile"
  },
  "onCreateCommand": "sudo chsh -s /usr/bin/zsh $USER",
  "features": {
    "ghcr.io/meaningful-ooo/devcontainer-features/homebrew:2": {}
  },
  "remoteEnv": {
    "MISE_GITHUB_TOKEN": "${localEnv:MISE_GITHUB_TOKEN}"
  },
  "postCreateCommand": "scripts/setup",
  "customizations": {
    "vscode": {
      "settings": {
        "terminal.integrated.defaultProfile.linux": "zsh",
        "terminal.integrated.profiles.linux": {
          "zsh": {
            "path": "/usr/bin/zsh"
          }
        }
      }
    }
  },
  "forwardPorts": [
    8080
  ]
}
